kombo_python/__init__.py
kombo_python/_version.py
kombo_python/assessment.py
kombo_python/ats.py
kombo_python/basesdk.py
kombo_python/connect.py
kombo_python/general.py
kombo_python/hris.py
kombo_python/httpclient.py
kombo_python/py.typed
kombo_python/sdk.py
kombo_python/sdkconfiguration.py
kombo_python/_hooks/__init__.py
kombo_python/_hooks/registration.py
kombo_python/_hooks/sdkhooks.py
kombo_python/_hooks/types.py
kombo_python/errors/__init__.py
kombo_python/errors/komboatserror.py
kombo_python/errors/kombogeneralerror.py
kombo_python/errors/kombohriserror.py
kombo_python/errors/no_response_error.py
kombo_python/errors/responsevalidationerror.py
kombo_python/errors/sdkdefaulterror.py
kombo_python/errors/sdkerror.py
kombo_python/models/__init__.py
kombo_python/models/assessmentorderreceivedwebhookpayload.py
kombo_python/models/connectionflowfailedwebhookpayload.py
kombo_python/models/datachangedwebhookpayload.py
kombo_python/models/deleteatscandidatescandidateidtagsop.py
kombo_python/models/deleteatscandidatescandidateidtagspositiveresponse.py
kombo_python/models/deleteatscandidatescandidateidtagsrequestbody.py
kombo_python/models/deletehrisabsencesabsenceidop.py
kombo_python/models/deletehrisabsencesabsenceidpositiveresponse.py
kombo_python/models/deletehrisabsencesabsenceidrequestbody.py
kombo_python/models/deleteintegrationsintegrationidop.py
kombo_python/models/deleteintegrationsintegrationidpositiveresponse.py
kombo_python/models/deleteintegrationsintegrationidrequestbody.py
kombo_python/models/getassessmentordersopenop.py
kombo_python/models/getassessmentordersopenpositiveresponse.py
kombo_python/models/getassessmentpackagesop.py
kombo_python/models/getassessmentpackagespositiveresponse.py
kombo_python/models/getatsapplicationsapplicationidattachmentsop.py
kombo_python/models/getatsapplicationsapplicationidattachmentspositiveresponse.py
kombo_python/models/getatsapplicationsop.py
kombo_python/models/getatsapplicationspositiveresponse.py
kombo_python-0.0.2.dist-info/METADATA
kombo_python-0.0.2.dist-info/WHEEL
kombo_python-0.0.2.dist-info/top_level.txt
kombo_python-0.0.2.dist-info/RECORD
