Metadata-Version: 2.4
Name: kombo-python
Version: 0.0.2
Summary: Python Client SDK Generated by Speakeasy.
Author: Speakeasy
Project-URL: repository, https://github.com/kombohq/python-sdk.git
Requires-Python: >=3.9.2
Requires-Dist: httpcore>=1.0.9
Requires-Dist: httpx>=0.28.1
Requires-Dist: jsonpath-python>=1.0.6
Requires-Dist: pydantic>=2.11.2
